aura/__init__.py
aura/context.py
aura/event.py
aura/manager.py
aura/service.py
mars-0.0.1.dist-info/LICENSE
mars-0.0.1.dist-info/METADATA
mars-0.0.1.dist-info/WHEEL
mars-0.0.1.dist-info/top_level.txt
mars-0.0.1.dist-info/RECORD
