Metadata-Version: 2.1
Name: mars
Version: 0.0.1
Summary: An eventing framework.
Home-page: https://github.com/polyaxon/polyaxon-cli
Author: Mourad Mourafiq
Author-email: mourad@polyaxon.com
Maintainer: Mourad Mourafiq
Maintainer-email: mourad@polyaxon.com
License: MIT
Keywords: mars,events,webhooks,async,aio,hooks,django,flask,web,services
Platform: any
Classifier: Programming Language :: Python
Classifier: Operating System :: OS Independent
Classifier: Intended Audience :: Developers
Classifier: Intended Audience :: Science/Research
Classifier: Topic :: Scientific/Engineering :: Artificial Intelligence
License-File: LICENSE
Requires-Dist: hestia >=0.2.0
